README.md
pyproject.toml
setup.py
PyAstronomy/PyA_Version.py
PyAstronomy/__init__.py
PyAstronomy/aitoffLegacy.py
PyAstronomy/ex_count_reset.py
PyAstronomy/ipynb_to_test.py
PyAstronomy.egg-info/PKG-INFO
PyAstronomy.egg-info/SOURCES.txt
PyAstronomy.egg-info/dependency_links.txt
PyAstronomy.egg-info/requires.txt
PyAstronomy.egg-info/top_level.txt
PyAstronomy/constants/__init__.py
PyAstronomy/constants/cdat.dat
PyAstronomy/constants/exampleSanity.py
PyAstronomy/constants/itc.py
PyAstronomy/doc/conf.py
PyAstronomy/doc/funcFit2Doc/sanity_ex_adding_two_gaussians.py
PyAstronomy/doc/funcFit2Doc/sanity_ex_algorestrict.py
PyAstronomy/doc/funcFit2Doc/sanity_ex_algorestrict_con.py
PyAstronomy/doc/funcFit2Doc/sanity_ex_apply_relation.py
PyAstronomy/doc/funcFit2Doc/sanity_ex_convenience_fit_1.py
PyAstronomy/doc/funcFit2Doc/sanity_ex_custom_objfct1.py
PyAstronomy/doc/funcFit2Doc/sanity_ex_emceesample_1.py
PyAstronomy/doc/funcFit2Doc/sanity_ex_gaussfit1.py
PyAstronomy/doc/funcFit2Doc/sanity_ex_linmod1.py
PyAstronomy/doc/funcFit2Doc/sanity_ex_linmod_jit.py
PyAstronomy/doc/funcFit2Doc/sanity_ex_model_evaluation.py
PyAstronomy/doc/funcFit2Doc/sanity_ex_parameter_access_1.py
PyAstronomy/doc/funcFit2Doc/sanity_ex_restrictviapenalties.py
PyAstronomy/doc/pyaslDoc/aslDoc/aslExt_1Doc/sanity_ex_sysrem_pca.py
PyAstronomy/doc/pyaslDoc/resBasedDoc/sanity_ex_speclib.py
PyAstronomy/dynamicSanity/extractExamples.py
PyAstronomy/funcFit/TutorialExampleSanity.py
PyAstronomy/funcFit/__init__.py
PyAstronomy/funcFit/anneal.py
PyAstronomy/funcFit/cauchyLorentz1d.py
PyAstronomy/funcFit/circle2d.py
PyAstronomy/funcFit/coordinateGrid.py
PyAstronomy/funcFit/extFitter.py
PyAstronomy/funcFit/fufDS.py
PyAstronomy/funcFit/funcFitSanity.py
PyAstronomy/funcFit/gauss1d.py
PyAstronomy/funcFit/gauss2d.py
PyAstronomy/funcFit/modelRebin.py
PyAstronomy/funcFit/moduleSanity.py
PyAstronomy/funcFit/nameIdentBase.py
PyAstronomy/funcFit/onedfit.py
PyAstronomy/funcFit/params.py
PyAstronomy/funcFit/polyModel.py
PyAstronomy/funcFit/sech.py
PyAstronomy/funcFit/sinexp1d.py
PyAstronomy/funcFit/syncFit.py
PyAstronomy/funcFit/voigt1d.py
PyAstronomy/funcFit/experimental/__init__.py
