Metadata-Version: 2.4
Name: PyAstronomy
Version: 0.24.0
Summary: A collection of astronomy related tools for Python.
Author-email: PyA group <stefan.czesla@hs.uni-hamburg.de>
License: MIT
Project-URL: Homepage, https://github.com/sczesla/PyAstronomy
Project-URL: Bug Tracker, https://github.com/sczesla/PyAstronomy/issues
Classifier: License :: OSI Approved :: MIT License
Classifier: Programming Language :: Python :: 3
Classifier: Operating System :: OS Independent
Classifier: Topic :: Scientific/Engineering :: Astronomy
Requires-Python: >=3.8
Requires-Dist: numpy
Requires-Dist: six
Requires-Dist: scipy
Requires-Dist: quantities
Requires-Dist: bidict
Provides-Extra: occult
Requires-Dist: PyAstronomy_ext; extra == "occult"
Provides-Extra: dev
Requires-Dist: pytest; extra == "dev"
Requires-Dist: build; extra == "dev"
Requires-Dist: twine; extra == "dev"
